markdowndocs/__init__.py
markdowndocs/cli.py
markdowndocs/constants.py
markdowndocs/md_utils.py
markdowndocs/mddocs.py
markdowndocs-0.1.1.dist-info/LICENSE
markdowndocs-0.1.1.dist-info/METADATA
markdowndocs-0.1.1.dist-info/WHEEL
markdowndocs-0.1.1.dist-info/entry_points.txt
markdowndocs-0.1.1.dist-info/top_level.txt
markdowndocs-0.1.1.dist-info/RECORD
