Metadata-Version: 2.1
Name: markdowndocs
Version: 0.1.1
Summary: A light-weight markdown code documentation generator
Home-page: https://github.com/ngoet/MarkdownDocs
Author: ngoet
Author-email: ndgoet@gmail.com
Classifier: Programming Language :: Python :: 3
Classifier: License :: OSI Approved :: MIT License
Classifier: Operating System :: OS Independent
License-File: LICENSE
Requires-Dist: tabulate>=0.8.7
Requires-Dist: pandas>=1.1.2
Requires-Dist: typer>=0.3.2
